hur_multimodal/__init__.py
hur_multimodal/hur_multimodal.py
hur_multimodal-1.0.9.dist-info/LICENSE.txt
hur_multimodal-1.0.9.dist-info/METADATA
hur_multimodal-1.0.9.dist-info/WHEEL
hur_multimodal-1.0.9.dist-info/top_level.txt
hur_multimodal-1.0.9.dist-info/RECORD
