Metadata-Version: 2.2
Name: hur_multimodal
Version: 1.0.9
Home-page: https://github.com/sapiens-technology/HurMultiModal
Author: SAPIENS TECHNOLOGY
License: Proprietary Software
License-File: LICENSE.txt
Requires-Dist: hurnet-torch
Requires-Dist: sapiens-tokenizer
Requires-Dist: sapiens-embedding
Requires-Dist: sapiens-attention
Requires-Dist: sapiens-infinite-context-window
Requires-Dist: sapiens-generalization
Requires-Dist: scn
Requires-Dist: torch
Requires-Dist: requests
Requires-Dist: ijson
Requires-Dist: tqdm
Requires-Dist: pillow
Requires-Dist: INFINITE-CONTEXT-WINDOW
Dynamic: author
Dynamic: home-page
Dynamic: license
Dynamic: requires-dist
